{
  "name": "Couturier",
  "type": "background",
  "img": "modules/troika-community-content/assets/tokens/backgrounds.svg",
  "system": {
    "armour": 1,
    "attribution": {
      "source": "Matt Umland [Troika! Community Jam: Backgrounds 2024]",
      "link": "https://www.mattumland.dev/"
    },
    "special": "<p>You may Test Your Luck to make any armour or outfit look absolutely fabulous.</p><p>Couturier is an independent production by Matt Umland and is not affiliated with the Melsonian Arts Council.</p>",
    "notes": "<p>A stunning outfit is never beyond your grasp. With enough pins and patience, even the most common burlap sack can be fit for the Autarch’s Fall Ball, though standards are higher for the Spring Fling. That would probably require the addition of a ribbon or two.</p>",
    "skill": "1d3+3",
    "stamina": "2d6+12",
    "luck": "1d6+6",
    "initiativeTokens": 2,
    "monies": "2d6",
    "provisions": {
      "p1": true,
      "p2": true,
      "p3": true,
      "p4": true,
      "p5": true,
      "p6": true,
      "p7": false,
      "p8": false,
      "p9": false,
      "p10": false,
      "p11": false,
      "p12": false
    }
  },
  "items": [
    {
      "name": "Fabric Scissors",
      "type": "gear",
      "img": "icons/svg/item-bag.svg",
      "system": {
        "description": "",
        "attack": {
          "dr1": "2",
          "dr2": "2",
          "dr3": "2",
          "dr4": "2",
          "dr5": "4",
          "dr6": "8",
          "dr7": "10"
        },
        "inventorySlots": 1,
        "sortOrder": -1,
        "canAttack": true,
        "equipped": true,
        "armourProvided": 0,
        "requiresTwoHands": false,
        "armourIgnored": 0,
        "quantity": 1,
        "attribution": {}
      },
      "effects": [],
      "flags": {},
      "_stats": {
        "systemId": "troika",
        "systemVersion": "0.2.7",
        "coreVersion": "10.291",
        "createdTime": 1676773918462,
        "modifiedTime": 1676827737963,
        "lastModifiedBy": "iubUFLpmPB0vkjXq"
      },
      "folder": null,
      "sort": 0,
      "ownership": {
        "default": 0,
        "iubUFLpmPB0vkjXq": 3
      },
      "_id": "2l6mWhe9TYoRc4CM",
      "_key": "!actors.items!1BJJElLUwIPVVkAn.2l6mWhe9TYoRc4CM"
    },
    {
      "name": "Sewing Notions",
      "type": "gear",
      "img": "modules/troika-community-content/assets/tokens/item.svg",
      "system": {
        "description": "<p>needles, pins, thread, measuring tape, buttons, snaps, patches, etc</p>",
        "inventorySlots": 1,
        "equipped": true,
        "quantity": 1,
        "attribution": {
          "source": "Matt Umland [Troika! Community Jam: Backgrounds 2024]",
          "link": "https://www.mattumland.dev/"
        },
        "canAttack": false,
        "attack": {
          "dr1": "2",
          "dr2": "2",
          "dr3": "2",
          "dr4": "2",
          "dr5": "4",
          "dr6": "8",
          "dr7": "10"
        },
        "sortOrder": -1,
        "armourProvided": 0,
        "requiresTwoHands": false,
        "armourIgnored": 0
      },
      "_id": "NL4nUAPV4W0dRzZm",
      "effects": [],
      "folder": null,
      "sort": 0,
      "ownership": {
        "default": 0
      },
      "flags": {},
      "_stats": {
        "systemId": null,
        "systemVersion": null,
        "coreVersion": null,
        "createdTime": null,
        "modifiedTime": null,
        "lastModifiedBy": null
      },
      "_key": "!actors.items!1BJJElLUwIPVVkAn.NL4nUAPV4W0dRzZm"
    },
    {
      "name": "Stunning, one-of-kind outfit.",
      "type": "gear",
      "system": {
        "inventorySlots": 1,
        "equipped": true,
        "quantity": 1,
        "description": "",
        "attribution": {
          "source": "Matt Umland [Troika! Community Jam: Backgrounds 2024]",
          "link": "https://www.mattumland.dev/"
        },
        "canAttack": false,
        "attack": {
          "dr1": "2",
          "dr2": "2",
          "dr3": "2",
          "dr4": "2",
          "dr5": "4",
          "dr6": "8",
          "dr7": "10"
        },
        "sortOrder": -1,
        "armourProvided": 0,
        "requiresTwoHands": false,
        "armourIgnored": 0
      },
      "_id": "gtQqKpOMOpiiW53I",
      "img": "icons/svg/item-bag.svg",
      "effects": [],
      "folder": null,
      "sort": 0,
      "ownership": {
        "default": 0
      },
      "flags": {},
      "_stats": {
        "systemId": null,
        "systemVersion": null,
        "coreVersion": null,
        "createdTime": null,
        "modifiedTime": null,
        "lastModifiedBy": null
      },
      "_key": "!actors.items!1BJJElLUwIPVVkAn.gtQqKpOMOpiiW53I"
    },
    {
      "name": "Another stunning, one-of-kind outfit.",
      "type": "gear",
      "system": {
        "inventorySlots": 1,
        "equipped": true,
        "quantity": 1,
        "description": "",
        "attribution": {
          "source": "Matt Umland [Troika! Community Jam: Backgrounds 2024]",
          "link": "https://www.mattumland.dev/"
        },
        "canAttack": false,
        "attack": {
          "dr1": "2",
          "dr2": "2",
          "dr3": "2",
          "dr4": "2",
          "dr5": "4",
          "dr6": "8",
          "dr7": "10"
        },
        "sortOrder": -1,
        "armourProvided": 0,
        "requiresTwoHands": false,
        "armourIgnored": 0
      },
      "_id": "puruo21A2WfWsRKR",
      "img": "icons/svg/item-bag.svg",
      "effects": [],
      "folder": null,
      "sort": 0,
      "ownership": {
        "default": 0
      },
      "flags": {},
      "_stats": {
        "systemId": null,
        "systemVersion": null,
        "coreVersion": null,
        "createdTime": null,
        "modifiedTime": null,
        "lastModifiedBy": null
      },
      "_key": "!actors.items!1BJJElLUwIPVVkAn.puruo21A2WfWsRKR"
    },
    {
      "name": "Manticore leather boots.",
      "type": "gear",
      "system": {
        "inventorySlots": 1,
        "equipped": true,
        "quantity": 1,
        "description": "",
        "attribution": {
          "source": "Matt Umland [Troika! Community Jam: Backgrounds 2024]",
          "link": "https://www.mattumland.dev/"
        },
        "canAttack": false,
        "attack": {
          "dr1": "2",
          "dr2": "2",
          "dr3": "2",
          "dr4": "2",
          "dr5": "4",
          "dr6": "8",
          "dr7": "10"
        },
        "sortOrder": -1,
        "armourProvided": 0,
        "requiresTwoHands": false,
        "armourIgnored": 0
      },
      "_id": "k5KewHsQNmQUwTIl",
      "img": "icons/svg/item-bag.svg",
      "effects": [],
      "folder": null,
      "sort": 0,
      "ownership": {
        "default": 0
      },
      "flags": {},
      "_stats": {
        "systemId": null,
        "systemVersion": null,
        "coreVersion": null,
        "createdTime": null,
        "modifiedTime": null,
        "lastModifiedBy": null
      },
      "_key": "!actors.items!1BJJElLUwIPVVkAn.k5KewHsQNmQUwTIl"
    },
    {
      "name": "Brocaded house shoes.",
      "type": "gear",
      "system": {
        "inventorySlots": 1,
        "equipped": true,
        "quantity": 1,
        "description": "",
        "attribution": {
          "source": "Matt Umland [Troika! Community Jam: Backgrounds 2024]",
          "link": "https://www.mattumland.dev/"
        },
        "canAttack": false,
        "attack": {
          "dr1": "2",
          "dr2": "2",
          "dr3": "2",
          "dr4": "2",
          "dr5": "4",
          "dr6": "8",
          "dr7": "10"
        },
        "sortOrder": -1,
        "armourProvided": 0,
        "requiresTwoHands": false,
        "armourIgnored": 0
      },
      "_id": "U1cB6sYf0wdifVwv",
      "img": "icons/svg/item-bag.svg",
      "effects": [],
      "folder": null,
      "sort": 0,
      "ownership": {
        "default": 0
      },
      "flags": {},
      "_stats": {
        "systemId": null,
        "systemVersion": null,
        "coreVersion": null,
        "createdTime": null,
        "modifiedTime": null,
        "lastModifiedBy": null
      },
      "_key": "!actors.items!1BJJElLUwIPVVkAn.U1cB6sYf0wdifVwv"
    },
    {
      "name": "Very large, boisterously festooned hat",
      "type": "gear",
      "system": {
        "description": "<p>counts as a helmet, lightly armoured</p>",
        "inventorySlots": 2,
        "equipped": true,
        "armourProvided": 1,
        "quantity": 1,
        "attribution": {},
        "canAttack": false,
        "attack": {
          "dr1": "2",
          "dr2": "2",
          "dr3": "2",
          "dr4": "2",
          "dr5": "4",
          "dr6": "8",
          "dr7": "10"
        },
        "sortOrder": -1,
        "requiresTwoHands": false,
        "armourIgnored": 0
      },
      "_id": "sKF2Cl6uMZO5hFDi",
      "img": "icons/svg/item-bag.svg",
      "effects": [],
      "folder": null,
      "sort": 0,
      "ownership": {
        "default": 0
      },
      "flags": {},
      "_stats": {
        "systemId": null,
        "systemVersion": null,
        "coreVersion": null,
        "createdTime": null,
        "modifiedTime": null,
        "lastModifiedBy": null
      },
      "_key": "!actors.items!1BJJElLUwIPVVkAn.sKF2Cl6uMZO5hFDi"
    },
    {
      "name": "Sewing",
      "type": "skill",
      "img": "modules/troika-community-content/assets/tokens/skill.svg",
      "system": {
        "description": "",
        "rank": 3,
        "attribution": {
          "source": "Matt Umland [Troika! Community Jam: Backgrounds 2024]",
          "link": "https://www.mattumland.dev/"
        },
        "canAttack": false,
        "attack": {
          "dr1": "2",
          "dr2": "2",
          "dr3": "2",
          "dr4": "2",
          "dr5": "4",
          "dr6": "8",
          "dr7": "10"
        },
        "modifier": 0,
        "improvement": false
      },
      "_id": "aPn6YSnxYtcc7zCV",
      "effects": [],
      "folder": null,
      "sort": 0,
      "ownership": {
        "default": 0
      },
      "flags": {},
      "_stats": {
        "systemId": null,
        "systemVersion": null,
        "coreVersion": null,
        "createdTime": null,
        "modifiedTime": null,
        "lastModifiedBy": null
      },
      "_key": "!actors.items!1BJJElLUwIPVVkAn.aPn6YSnxYtcc7zCV"
    },
    {
      "name": "Scissor Fighting",
      "type": "skill",
      "img": "modules/troika-community-content/assets/tokens/skill.svg",
      "system": {
        "description": "",
        "rank": 2,
        "attribution": {
          "source": "Matt Umland [Troika! Community Jam: Backgrounds 2024]",
          "link": "https://www.mattumland.dev/"
        },
        "canAttack": false,
        "attack": {
          "dr1": "2",
          "dr2": "2",
          "dr3": "2",
          "dr4": "2",
          "dr5": "4",
          "dr6": "8",
          "dr7": "10"
        },
        "modifier": 0,
        "improvement": false
      },
      "_id": "MBDhRrYiQ2lkPgKu",
      "effects": [],
      "folder": null,
      "sort": 0,
      "ownership": {
        "default": 0
      },
      "flags": {},
      "_stats": {
        "systemId": null,
        "systemVersion": null,
        "coreVersion": null,
        "createdTime": null,
        "modifiedTime": null,
        "lastModifiedBy": null
      },
      "_key": "!actors.items!1BJJElLUwIPVVkAn.MBDhRrYiQ2lkPgKu"
    },
    {
      "name": "Disguise",
      "type": "skill",
      "img": "icons/svg/book.svg",
      "system": {
        "description": "<p id=\"docs-internal-guid-56976a83-7fff-5674-fe85-6827a739c7d1\" dir=\"ltr\"><span id=\"docs-internal-guid-3270f137-7fff-a5be-8ca9-e60768966dcf\">Covers the use of props to change your appearance. When in disguise you must Roll Under this when someone is liable to see through it. Opposed by Awareness when under scrutiny. </span></p>",
        "attack": {
          "dr1": "2",
          "dr2": "2",
          "dr3": "2",
          "dr4": "2",
          "dr5": "4",
          "dr6": "8",
          "dr7": "10"
        },
        "rank": 2,
        "modifier": 0,
        "improvement": false,
        "canAttack": false,
        "attribution": {}
      },
      "effects": [],
      "flags": {
        "core": {
          "sourceId": "Item.cF40jXjQ3ql3R4u4"
        }
      },
      "_stats": {
        "systemId": "troika",
        "systemVersion": "0.2.7",
        "coreVersion": "10.291",
        "createdTime": 1676781942840,
        "modifiedTime": 1676782632706,
        "lastModifiedBy": "iubUFLpmPB0vkjXq"
      },
      "folder": null,
      "sort": 0,
      "ownership": {
        "default": 0,
        "iubUFLpmPB0vkjXq": 3
      },
      "_id": "n46l19X9LKRMiTWI",
      "_key": "!actors.items!1BJJElLUwIPVVkAn.n46l19X9LKRMiTWI"
    },
    {
      "name": "Etiquette",
      "type": "skill",
      "img": "icons/svg/book.svg",
      "system": {
        "description": "<p id=\"docs-internal-guid-56976a83-7fff-5674-fe85-6827a739c7d1\" dir=\"ltr\"><span id=\"docs-internal-guid-e9394963-7fff-eef3-dd48-43e58195b62a\">When making a good impression is important Roll Versus your host&rsquo;s Etiquette. Represents a mechanical understanding of social conduct and those who are better at it are more discerning.</span></p>",
        "attack": {
          "dr1": "2",
          "dr2": "2",
          "dr3": "2",
          "dr4": "2",
          "dr5": "4",
          "dr6": "8",
          "dr7": "10"
        },
        "rank": 2,
        "modifier": 0,
        "improvement": false,
        "canAttack": false,
        "attribution": {}
      },
      "effects": [],
      "flags": {
        "core": {
          "sourceId": "Item.cF40jXjQ3ql3R4u4"
        }
      },
      "_stats": {
        "systemId": "troika",
        "systemVersion": "0.2.7",
        "coreVersion": "10.291",
        "createdTime": 1676781942840,
        "modifiedTime": 1676782632706,
        "lastModifiedBy": "iubUFLpmPB0vkjXq"
      },
      "folder": null,
      "sort": 0,
      "ownership": {
        "default": 0,
        "iubUFLpmPB0vkjXq": 3
      },
      "_id": "aipqHGexIQdhs9CP",
      "_key": "!actors.items!1BJJElLUwIPVVkAn.aipqHGexIQdhs9CP"
    },
    {
      "name": "Affix",
      "type": "spell",
      "img": "icons/svg/daze.svg",
      "system": {
        "description": "<p id=\"docs-internal-guid-95655f34-7fff-c9ce-bad4-f83454db0015\" dir=\"ltr\">Cause a subject to be fixed in place. While they are so held they do not</p>\n<p dir=\"ltr\">move, breathe, fall, perspire, acquire, or otherwise change. They are totally</p>\n<p dir=\"ltr\">immune to harm, in fact. Lasts for 3 minutes.</p>",
        "attack": {
          "dr1": "2",
          "dr2": "2",
          "dr3": "2",
          "dr4": "2",
          "dr5": "4",
          "dr6": "8",
          "dr7": "10"
        },
        "rank": 1,
        "castingCost": "3",
        "modifier": 0,
        "improvement": false,
        "canAttack": false,
        "attribution": {}
      },
      "effects": [],
      "flags": {},
      "_stats": {
        "systemId": "troika",
        "systemVersion": "0.2.7",
        "coreVersion": "10.291",
        "createdTime": 1673720934918,
        "modifiedTime": 1676771738835,
        "lastModifiedBy": "iubUFLpmPB0vkjXq"
      },
      "folder": null,
      "sort": 0,
      "ownership": {
        "default": 0,
        "iubUFLpmPB0vkjXq": 3
      },
      "_id": "uAvXsKDHW23nmZ8G",
      "_key": "!actors.items!1BJJElLUwIPVVkAn.uAvXsKDHW23nmZ8G"
    },
    {
      "name": "Helping Hands",
      "type": "spell",
      "img": "icons/svg/daze.svg",
      "system": {
        "description": "<p><span dir=\"ltr\" role=\"presentation\">Animate hands spring forth from an inanimate surface and perform any </span><span dir=\"ltr\" role=\"presentation\">task the wizard requires but are limited to being rooted to the spot from </span><span dir=\"ltr\" role=\"presentation\">which they sprang. They last until the wizard wills it or leaves the location.</span></p>",
        "attack": {
          "dr1": "2",
          "dr2": "2",
          "dr3": "2",
          "dr4": "2",
          "dr5": "4",
          "dr6": "8",
          "dr7": "10"
        },
        "rank": 1,
        "castingCost": "1",
        "modifier": 0,
        "improvement": false,
        "canAttack": false,
        "attribution": {}
      },
      "effects": [],
      "flags": {},
      "_stats": {
        "systemId": "troika",
        "systemVersion": "0.2.7",
        "coreVersion": "10.291",
        "createdTime": 1676769709810,
        "modifiedTime": 1676771738841,
        "lastModifiedBy": "iubUFLpmPB0vkjXq"
      },
      "folder": null,
      "sort": 0,
      "ownership": {
        "default": 0,
        "iubUFLpmPB0vkjXq": 3
      },
      "_id": "Wf1wkqLdbCiWWS37",
      "_key": "!actors.items!1BJJElLUwIPVVkAn.Wf1wkqLdbCiWWS37"
    }
  ],
  "folder": "VQDsap64MLlBCSLh",
  "_id": "1BJJElLUwIPVVkAn",
  "prototypeToken": {
    "name": "Couturier",
    "displayName": 0,
    "actorLink": false,
    "appendNumber": false,
    "prependAdjective": false,
    "texture": {
      "src": "icons/svg/mystery-man.svg",
      "scaleX": 1,
      "scaleY": 1,
      "offsetX": 0,
      "offsetY": 0,
      "rotation": 0
    },
    "width": 1,
    "height": 1,
    "lockRotation": false,
    "rotation": 0,
    "alpha": 1,
    "disposition": -1,
    "displayBars": 0,
    "bar1": {
      "attribute": "stamina"
    },
    "bar2": {
      "attribute": "luck"
    },
    "light": {
      "alpha": 0.5,
      "angle": 360,
      "bright": 0,
      "coloration": 1,
      "dim": 0,
      "attenuation": 0.5,
      "luminosity": 0.5,
      "saturation": 0,
      "contrast": 0,
      "shadows": 0,
      "animation": {
        "type": null,
        "speed": 5,
        "intensity": 5,
        "reverse": false
      },
      "darkness": {
        "min": 0,
        "max": 1
      }
    },
    "sight": {
      "enabled": false,
      "range": 0,
      "angle": 360,
      "visionMode": "basic",
      "attenuation": 0.1,
      "brightness": 0,
      "saturation": 0,
      "contrast": 0
    },
    "detectionModes": [],
    "flags": {},
    "randomImg": false
  },
  "effects": [],
  "sort": 0,
  "ownership": {
    "default": 0,
    "7IDFZvOGXqWmmgkb": 3
  },
  "flags": {},
  "_stats": {
    "systemId": "troika",
    "systemVersion": "1.5.0",
    "coreVersion": "11.315",
    "createdTime": 1723905256111,
    "modifiedTime": 1723905256111,
    "lastModifiedBy": "7IDFZvOGXqWmmgkb"
  },
  "_key": "!actors!1BJJElLUwIPVVkAn"
}
